ScoutSuite/__init__.py
ScoutSuite/__main__.py
ScoutSuite/utils.py
ScoutSuite/core/__init__.py
ScoutSuite/core/cli_parser.py
ScoutSuite/core/conditions.py
ScoutSuite/core/console.py
ScoutSuite/core/exceptions.py
ScoutSuite/core/fs.py
ScoutSuite/core/processingengine.py
ScoutSuite/core/rule.py
ScoutSuite/core/rule_definition.py
ScoutSuite/core/ruleset.py
ScoutSuite/core/server.py
ScoutSuite/core/utils.py
ScoutSuite/data/icmp_message_types.json
ScoutSuite/data/protocols.json
ScoutSuite/data/aws/ip-ranges/aws-in-ec2.json
ScoutSuite/data/aws/ip-ranges/aws-in-us.json
ScoutSuite/data/aws/ip-ranges/aws.json
ScoutSuite/output/__init__.py
ScoutSuite/output/html.py
ScoutSuite/output/result_encoder.py
ScoutSuite/output/utils.py
ScoutSuite/output/data/includes.zip
ScoutSuite/output/data/html/report.html
ScoutSuite/output/data/html/conditionals/json_format.html
ScoutSuite/output/data/html/conditionals/sqlite_format.html
ScoutSuite/output/data/html/partials/about_scoutsuite.html
ScoutSuite/output/data/html/partials/accordion.html
ScoutSuite/output/data/html/partials/accordion_policy.html
ScoutSuite/output/data/html/partials/count_badge.html
ScoutSuite/output/data/html/partials/dashboard.html
ScoutSuite/output/data/html/partials/details.html
ScoutSuite/output/data/html/partials/details_for_region.html
ScoutSuite/output/data/html/partials/details_for_vpc.html
ScoutSuite/output/data/html/partials/ec2_grants.html
ScoutSuite/output/data/html/partials/filters.html
ScoutSuite/output/data/html/partials/generic_object.html
ScoutSuite/output/data/html/partials/ip_grants.html
ScoutSuite/output/data/html/partials/last_run_details.html
ScoutSuite/output/data/html/partials/left_menu.html
ScoutSuite/output/data/html/partials/metadata.html
ScoutSuite/output/data/html/partials/modal.html
ScoutSuite/output/data/html/partials/network_interface.html
ScoutSuite/output/data/html/partials/policy.html
ScoutSuite/output/data/html/partials/report_footer.html
ScoutSuite-5.14.0.dist-info/LICENSE
ScoutSuite-5.14.0.dist-info/METADATA
ScoutSuite-5.14.0.dist-info/WHEEL
ScoutSuite-5.14.0.dist-info/entry_points.txt
ScoutSuite-5.14.0.dist-info/top_level.txt
ScoutSuite-5.14.0.dist-info/RECORD
