Metadata-Version: 2.1
Name: ScoutSuite
Version: 5.14.0
Summary: Scout Suite, a multi-cloud security auditing tool
Home-page: https://github.com/nccgroup/ScoutSuite
Author: NCC Group
License: GNU General Public License v2 (GPLv2)
Classifier: Development Status :: 5 - Production/Stable
Classifier: Intended Audience :: Developers
Classifier: Intended Audience :: Information Technology
Classifier: Intended Audience :: System Administrators
Classifier: Natural Language :: English
Classifier: License :: OSI Approved :: GNU General Public License v2 (GPLv2)
Classifier: Programming Language :: Python
Classifier: Programming Language :: Python :: 3
Classifier: Programming Language :: Python :: 3.9
Classifier: Programming Language :: Python :: 3.10
Classifier: Programming Language :: Python :: 3.11
License-File: LICENSE
Requires-Dist: python-dateutil<2.8.1,>=2.1
Requires-Dist: netaddr>=0.8.0
Requires-Dist: sqlitedict>=1.6.0
Requires-Dist: cherrypy>=18.1.0
Requires-Dist: cherrypy-cors>=1.6
Requires-Dist: coloredlogs<=10.0
Requires-Dist: asyncio-throttle==0.1.1
Requires-Dist: botocore>=1.20.21
Requires-Dist: boto3>=1.9.210
Requires-Dist: policyuniverse>=1.3.2.0
Requires-Dist: grpcio>=1.18.0
Requires-Dist: google-cloud-container>=2.1.0
Requires-Dist: google-cloud-core>=0.29.1
Requires-Dist: google-cloud-iam>=0.1.0
Requires-Dist: google-cloud-logging>=2.2.0
Requires-Dist: google-cloud-monitoring==1.1.0
Requires-Dist: google-cloud-resource-manager>=0.28.3
Requires-Dist: google-cloud-storage>=1.13.2
Requires-Dist: google-cloud-kms==1.3.0
Requires-Dist: google-api-python-client>=2.47.0
Requires-Dist: oauth2client>=4.1.3
Requires-Dist: httplib2shim>=0.0.3
Requires-Dist: azure-identity==1.5.0
Requires-Dist: azure-mgmt-resource==15.0.0
Requires-Dist: azure-mgmt-storage==17.0.0
Requires-Dist: azure-mgmt-monitor==2.0.0
Requires-Dist: azure-mgmt-sql==1.0.0
Requires-Dist: azure-mgmt-security==1.0.0
Requires-Dist: azure-mgmt-keyvault==8.0.0
Requires-Dist: azure-mgmt-network==17.1.0
Requires-Dist: azure-mgmt-redis==12.0.0
Requires-Dist: azure-mgmt-web==1.0.0
Requires-Dist: azure-mgmt-compute==18.2.0
Requires-Dist: azure-mgmt-authorization==3.0.0
Requires-Dist: azure-mgmt-rdbms==8.0.0
Requires-Dist: msgraph-core==0.2.2
Requires-Dist: aliyun-python-sdk-core>=2.13.4
Requires-Dist: aliyun-python-sdk-ram>=3.0.1
Requires-Dist: aliyun-python-sdk-ocs>=0.0.4
Requires-Dist: aliyun-python-sdk-sts>=3.0.1
Requires-Dist: aliyun-python-sdk-actiontrail>=2.0.0
Requires-Dist: aliyun-python-sdk-vpc>=3.0.5
Requires-Dist: aliyun-python-sdk-ecs>=4.16.10
Requires-Dist: aliyun-python-sdk-rds>=2.3.9
Requires-Dist: aliyun-python-sdk-kms>=2.6.0
Requires-Dist: oss2>=2.8.0
Requires-Dist: oci>=2.2.4
Requires-Dist: kubernetes
Requires-Dist: pydo>=0.2.0
